xdTelegramMsgAPI/__init__.py
xdTelegramMsgAPI/xdtelegram.py
xdtelegrammsgapi-0.1.0.dist-info/licenses/LICENSE
xdtelegrammsgapi-0.1.0.dist-info/METADATA
xdtelegrammsgapi-0.1.0.dist-info/WHEEL
xdtelegrammsgapi-0.1.0.dist-info/top_level.txt
xdtelegrammsgapi-0.1.0.dist-info/RECORD
