Metadata-Version: 2.4
Name: xdTelegramMsgAPI
Version: 0.1.0
Summary: A Python library for sending messages via the xd-org.site Telegram API
Home-page: https://github.com/ayushbiswas007/xdTelegramMsgAPI
Author: Ayush Biswas
Author-email: adgaming780@gmail.com
Classifier: Programming Language :: Python :: 3
Classifier: License :: OSI Approved :: MIT License
Classifier: Operating System :: OS Independent
Requires-Python: >=3.6
License-File: LICENSE
Requires-Dist: requests>=2.25.0
Dynamic: author
Dynamic: author-email
Dynamic: classifier
Dynamic: description
Dynamic: description-content-type
Dynamic: home-page
Dynamic: license-file
Dynamic: requires-dist
Dynamic: requires-python
Dynamic: summary
